Workbook

Sheet Summary
A1: IRCTC Train Ticket Booking: End-to-End Test Case Document
A10: Results by module
A11: Module | B11: Total | C11: Pass | D11: Fail | E11: Blocked | F11: Not Run | G11: Not Executed (designed only)
A12: Search | B12: =COUNTIF('Test Cases'!$B$2:$B$300,A12) -> 13 | C12: =COUNTIFS('Test Cases'!$B$2:$B$300,$A12,'Test Cases'!$L$2:$L$300,"Pass") -> 8 | D12: =COUNTIFS('Test Cases'!$B$2:$B$300,$A12,'Test Cases'!$L$2:$L$300,"Fail") -> 3 | E12: =COUNTIFS('Test Cases'!$B$2:$B$300,$A12,'Test Cases'!$L$2:$L$300,"Blocked") -> 1 | F12: =COUNTIFS('Test Cases'!$B$2:$B$300,$A12,'Test Cases'!$L$2:$L$300,"Not Run") -> 1 | G12: =COUNTIFS('Test Cases'!$B$2:$B$300,$A12,'Test Cases'!$L$2:$L$300,"Not Executed") -> 0
A13: Login | B13: =COUNTIF('Test Cases'!$B$2:$B$300,A13) -> 12 | C13: =COUNTIFS('Test Cases'!$B$2:$B$300,$A13,'Test Cases'!$L$2:$L$300,"Pass") -> 10 | D13: =COUNTIFS('Test Cases'!$B$2:$B$300,$A13,'Test Cases'!$L$2:$L$300,"Fail") -> 0 | E13: =COUNTIFS('Test Cases'!$B$2:$B$300,$A13,'Test Cases'!$L$2:$L$300,"Blocked") -> 0 | F13: =COUNTIFS('Test Cases'!$B$2:$B$300,$A13,'Test Cases'!$L$2:$L$300,"Not Run") -> 0 | G13: =COUNTIFS('Test Cases'!$B$2:$B$300,$A13,'Test Cases'!$L$2:$L$300,"Not Executed") -> 2
A14: Train Selection | B14: =COUNTIF('Test Cases'!$B$2:$B$300,A14) -> 9 | C14: =COUNTIFS('Test Cases'!$B$2:$B$300,$A14,'Test Cases'!$L$2:$L$300,"Pass") -> 9 | D14: =COUNTIFS('Test Cases'!$B$2:$B$300,$A14,'Test Cases'!$L$2:$L$300,"Fail") -> 0 | E14: =COUNTIFS('Test Cases'!$B$2:$B$300,$A14,'Test Cases'!$L$2:$L$300,"Blocked") -> 0 | F14: =COUNTIFS('Test Cases'!$B$2:$B$300,$A14,'Test Cases'!$L$2:$L$300,"Not Run") -> 0 | G14: =COUNTIFS('Test Cases'!$B$2:$B$300,$A14,'Test Cases'!$L$2:$L$300,"Not Executed") -> 0
A15: Passenger Details | B15: =COUNTIF('Test Cases'!$B$2:$B$300,A15) -> 13 | C15: =COUNTIFS('Test Cases'!$B$2:$B$300,$A15,'Test Cases'!$L$2:$L$300,"Pass") -> 10 | D15: =COUNTIFS('Test Cases'!$B$2:$B$300,$A15,'Test Cases'!$L$2:$L$300,"Fail") -> 0 | E15: =COUNTIFS('Test Cases'!$B$2:$B$300,$A15,'Test Cases'!$L$2:$L$300,"Blocked") -> 3 | F15: =COUNTIFS('Test Cases'!$B$2:$B$300,$A15,'Test Cases'!$L$2:$L$300,"Not Run") -> 0 | G15: =COUNTIFS('Test Cases'!$B$2:$B$300,$A15,'Test Cases'!$L$2:$L$300,"Not Executed") -> 0
A16: Payment | B16: =COUNTIF('Test Cases'!$B$2:$B$300,A16) -> 11 | C16: =COUNTIFS('Test Cases'!$B$2:$B$300,$A16,'Test Cases'!$L$2:$L$300,"Pass") -> 1 | D16: =COUNTIFS('Test Cases'!$B$2:$B$300,$A16,'Test Cases'!$L$2:$L$300,"Fail") -> 0 | E16: =COUNTIFS('Test Cases'!$B$2:$B$300,$A16,'Test Cases'!$L$2:$L$300,"Blocked") -> 0 | F16: =COUNTIFS('Test Cases'!$B$2:$B$300,$A16,'Test Cases'!$L$2:$L$300,"Not Run") -> 0 | G16: =COUNTIFS('Test Cases'!$B$2:$B$300,$A16,'Test Cases'!$L$2:$L$300,"Not Executed") -> 10
A17: Booking Confirmation | B17: =COUNTIF('Test Cases'!$B$2:$B$300,A17) -> 8 | C17: =COUNTIFS('Test Cases'!$B$2:$B$300,$A17,'Test Cases'!$L$2:$L$300,"Pass") -> 0 | D17: =COUNTIFS('Test Cases'!$B$2:$B$300,$A17,'Test Cases'!$L$2:$L$300,"Fail") -> 0 | E17: =COUNTIFS('Test Cases'!$B$2:$B$300,$A17,'Test Cases'!$L$2:$L$300,"Blocked") -> 0 | F17: =COUNTIFS('Test Cases'!$B$2:$B$300,$A17,'Test Cases'!$L$2:$L$300,"Not Run") -> 0 | G17: =COUNTIFS('Test Cases'!$B$2:$B$300,$A17,'Test Cases'!$L$2:$L$300,"Not Executed") -> 8
A18: Total | B18: =SUM(B12:B17) -> 66 | C18: =SUM(C12:C17) -> 38 | D18: =SUM(D12:D17) -> 3 | E18: =SUM(E12:E17) -> 4 | F18: =SUM(F12:F17) -> 1 | G18: =SUM(G12:G17) -> 20
A20: Pass rate (of executed) | B20: =IF((C18+D18)=0,0,C18/(C18+D18)) -> 0.92682927
A22: How to use this workbook
A23: 1. 'Test Cases' sheet: cases marked 'Executed' were run on the live site. Actual Result, Status (Pass / Fail / Blocked) and Remarks (with screenshots) are filled in.
A24: 2. Cases marked 'Designed (not executed)' cover stages that need a real payment or booking, so they were not run. They are derived from analysis of the journey and standard IRCTC behaviour. Their Status is 'Not Executed'.
A25: 3. Counts on this sheet update automatically from the Status column in the 'Test Cases' sheet.
A26: 4. Blocked means the case was started on the live site but could not be completed. The reason is given in Remarks.
A27: 5. Defects found during testing are logged in the 'Defect Log' sheet.

Sheet Test Cases
A1: TC ID | B1: Module | C1: Scenario | D1: Type | E1: Priority | F1: Preconditions | G1: Test Steps | H1: Test Data | I1: Expected Result | J1: Execution Mode | K1: Actual Result | L1: Status | M1: Remarks / Screenshot
A2: TC_S01 | B2: Search | C2: Valid search with all mandatory fields | D2: Positive | E2: High | F2: IRCTC website open (irctc.co.in) | G2: 1. Enter From station 2. Enter To station 3. Select a future date 4. Click Search | H2: From: Ernakulam Jn (ERS); To: Thiruvananthapuram Central (TVC); Date: today (01 Oct 2026); Class: All; Quota: General | I2: Train list page loads with trains running between the stations on that date | J2: Executed | K2: Train list loaded with 31 results for ERS to TVC, Thu 01 Oct 2026, All Classes, General quota. Each card shows departure/arrival, duration, running days and class tiles (availability shown only after clicking a class). Nearby stations (Ernakulam Town, Trivandrum North) also appear. | L2: Pass | M2: View screenshot
A3: TC_S02 | B3: Search | C3: Station autosuggest works | D3: Positive | E3: Medium | F3: IRCTC website open (irctc.co.in) | G3: 1. Type 'Ernak' in From field 2. Select a suggestion | H3: Partial text: 'Ernak', 'ERS' | I3: Matching stations are suggested; selecting one fills the field with name and code | J3: Executed | K3: Typed "ern" in the From field. A dropdown appeared while typing, with Ernakulam Town (ERN), a "Journeys" section showing a recent route (Ernakulam Jn to Thiruvananthapuram C), and a "Stations" section listing Ernakulam Jn (ERS), Pernem (PERN, Goa) and Serndanur (SXR, Tamil Nadu). Each suggestion shows the station name, code and state. Matches appear for text inside the name, not only the start | L3: Pass | M3: View screenshot
A4: TC_S03 | B4: Search | C4: Same From and To station | D4: Negative | E4: High | F4: IRCTC website open (irctc.co.in) | G4: 1. Enter same station in From and To 2. Click Search | H4: From = To = ERS | I4: Error message shown; search is not performed | J4: Executed | K4: Entered Ernakulam Jn (ERS) in both From and To and clicked Search Trains. The search was not blocked and no error message about identical stations was shown. On the first attempt nothing happened on screen. On the next attempt a "no trains found" page was displayed (message: "No Trains found for the selected route."). The user gets no clear explanation that From and To cannot be the same. | L4: Fail | M4: View Screenshot
A5: TC_S04 | B5: Search | C5: Search with empty From/To | D5: Negative | E5: High | F5: IRCTC website open (irctc.co.in) | G5: 1. Leave From/To blank 2. Click Search | H5: Blank | I5: Mandatory-field validation message; no search | J5: Executed | K5: Left From and To empty and clicked Search Trains. No message or highlight appeared and the page stayed the same. The user gets no indication of what is missing | L5: Fail | M5: View Screenshot
A6: TC_S05 | B6: Search | C6: Invalid station text | D6: Negative | E6: Medium | F6: IRCTC website open (irctc.co.in) | G6: 1. Type random text in From 2. Observe suggestions 3. Click Search | H6: 'XYZ123' | I6: No suggestions; search blocked with a message | J6: Executed | K6: Typed "XYZ123" in the From field and selected Ernakulam Jn in To. No station suggestions appeared, and the From field kept the invalid text without any warning. Clicking Search Trains [nothing happened / showed a "no trains found" page]. No error message about an invalid station was displayed | L6: Fail | M6: View screenshot
A7: TC_S06 | B7: Search | C7: Past date selection | D7: Negative | E7: High | F7: IRCTC website open (irctc.co.in) | G7: 1. Open the date picker 2. Try to select yesterday | H7: Yesterday's date | I7: Past dates are disabled or an error is shown | J7: Executed | K7: Opened the date picker and tried to select yesterday (30 Sep 2026). Past dates are disabled in the calendar and cannot be clicked; only today and future dates can be selected. | L7: Pass | M7: View Screenshot
A8: TC_S07 | B8: Search | C8: Boundary: last allowed booking date | D8: Boundary | E8: High | F8: IRCTC website open (irctc.co.in) | G8: 1. Select the last day in the advance reservation window (60 days, excluding the journey day; verify on site) 2. Search | H8: Date = today + 60 days | I8: Results are displayed | J8: Executed | K8: Opened the date picker and moved forward to December 2026. The last selectable date was 03 Dec 2026 (63 days from today, 01 Oct 2026). Searched for this date: [trains were listed / no trains found] | L8: Pass | M8: View Screenshot
A9: TC_S08 | B9: Search | C9: Boundary: one day beyond booking window | D9: Boundary | E9: High | F9: IRCTC website open (irctc.co.in) | G9: 1. Try selecting today + 61 days | H9: Date = today + 61 days | I9: Date not selectable or a clear message is displayed | J9: Executed | K9: The day after the last allowed date (04 Dec 2026) and all later dates are greyed out and cannot be selected. | L9: Pass | M9: View Screenshot
A10: TC_S09 | B10: Search | C10: Swap From and To | D10: Positive | E10: Low | F10: IRCTC website open (irctc.co.in) | G10: 1. Fill From and To 2. Click swap icon | H10: ERS / TVC | I10: Values are exchanged correctly | J10: Executed | K10: Entered Ernakulam Jn (ERS) in From and Thiruvananthapuram Central (TVC) in To, then clicked the swap arrows. The two stations were exchanged correctly (From became TVC, To became ERS). Clicking Search Trains afterwards loaded the results for the swapped route. | L10: Pass | M10: View Screenshot
A11: TC_S10 | B11: Search | C11: Class and quota selection | D11: Positive | E11: Medium | F11: IRCTC website open (irctc.co.in) | G11: 1. Choose a class (e.g., 3A) and quota (General, Ladies, Tatkal, Senior Citizen) 2. Search | H11: Class: 3A; Quota: General | I11: Results reflect selected class and quota | J11: Executed | K11: Selected class 3A (AC 3 Tier) and quota GENERAL, then clicked Search Trains. The results showed trains with 3A availability for the selected route and quota. | L11: Pass | M11: View Screenshot
A12: TC_S11 | B12: Search | C12: No trains available for the route | D12: Negative | E12: Medium | F12: IRCTC website open (irctc.co.in) | G12: 1. Search a route with no direct train | H12: Two stations with no direct service | I12: Clear 'no trains found' message; page does not crash | J12: Executed | K12: Entered Ernakulam Jn (ERS) in From and Port Blair in To, then clicked Search Trains. Nothing happened: the page stayed on the same search screen with no results and no message. Port Blair has no railway station, so this was not a valid "no direct train" route. Could not find a valid route with no direct service on the live site. | L12: Blocked | M12: View Screenshot
... A66: TC_B08 | B66: Booking Confirmation | C66: Cancellation option and refund rules shown | D66: Positive | E66: Medium | F66: Ticket booked | G66: 1. Open cancel option (do not cancel a real ticket) | H66: Booked ticket PNR; cancel option opened only to view the refund rules, not confirmed | I66: Cancellation available; refund rules displayed | J66: Designed (not executed) | K66: Not executed: requires an existing booked ticket to open the cancel option. Cancelling a real ticket is not performed. | L66: Not Executed | M66: Designed from analysis. Expected behaviour: the cancel option is available for the booked ticket and the refund rules are shown before confirmation. Rules as per project source: more than 72 hours before departure, flat standard fee only (varies by class); 72 to 24 hours, 25% of total fare; 24 to 8 hours, 50% of total fare; less than 8 hours, no refund for confirmed tickets. Stop at the cancellation screen and do not confirm. Verify the rules on the live site.
A67: TC_S12 | B67: Search | C67: Search for today's date lists trains that have already departed | D67: Negative | E67: Medium | F67: IRCTC website open | G67: 1. Search a route for today's date late in the day 2. Click a class tile on an early-morning train 3. Click Book Now | H67: ERS to TVC; today's date; train departing 00:07 | I67: Departed trains are hidden, or booking is clearly blocked with a message | J67: Executed | L67: Not Run | M67: Added from own observation of TC_S01 results

Sheet Assumptions & Rules
A1: # | B1: Assumption / business rule used | C1: Source / how to verify
A2: 1 | B2: Advance reservation period is 60 days, excluding the journey date; general booking opens at 8:00 AM IST. | C2: Publicly reported 2026 IRCTC rules. Verify in the date picker on the live site.
A3: 2 | B3: Tatkal opens one day before journey: 10:00 AM for AC classes, 11:00 AM for non-AC classes. | C3: IRCTC Tatkal booking guide and 2026 rule summaries. Verify on site.
A4: 3 | B4: Maximum 6 passengers per PNR in general quota; maximum 4 per PNR in Tatkal. | C4: IRCTC Tatkal guide (4 per PNR) and 2026 rule summaries. Verify on the passenger page.
A5: 4 | B5: Senior citizen concession is not available on Tatkal tickets. | C5: 2026 rule summaries. Verify on site.
A6: 5 | B6: Tatkal booking may require Aadhaar-based authentication for the user ID. | C6: Reported 2025-26 change. Verify on site before relying on it.
A7: 6 | B7: No real payment, booking or cancellation was performed. Payment and Confirmation cases are designed from analysis. | C7: Stated in the task brief: stages that cannot be directly executed.
A8: 7 | B8: Test environment: live public site, a personal test user account, no load or security penetration testing. | C8: -

Sheet Defect Log
A1: Bug ID | B1: Module | C1: Title | D1: Steps to Reproduce | E1: Expected Result | F1: Actual Result | G1: Severity | H1: Priority | I1: Status | J1: Screenshot
A2: BUG_01 | B2: Search | C2: (Example) Sample defect title: replace with a real finding | D2: 1. Open site 2. Do X 3. Observe Y | E2: What should happen | F2: What actually happened | G2: Minor | H2: Low | I2: New | J2: Attach file name

Sheet Evidence
A1: TC_S01: Valid search
A27: TC_S02: Station autosuggest
A56: TC_S03 | B56: Same From and To
A84: TC_S04 (empty From/To)
A108: TC_S05: Invalid station text
A130: TC_S06: Past date selection
A153: TC_S07: Boundary: last allowed booking date
A178: TC_S08:Boundary: one day beyond booking window
A203: TC_S09:Swap From and To
A234: TC_S10:Class and quota selection
A265: TC_S11 :no trains for a route
A295: TC_L01: Login with valid credentials
A351: TC_L02:Login with wrong password
A382: TC_L03: Login with unregistered user ID
A408: TC_L04:Login with blank fields
... A1117: TC_PAY04
